investaholic_common/classes/__init__.py
investaholic_common/classes/position.py
investaholic_common/classes/proposal.py
investaholic_common/classes/risk.py
investaholic_common/classes/ticker.py
investaholic_common/classes/user.py
investaholic_common/errors/errors.py
investaholic_common/representation/__init__.py
investaholic_common/representation/position_representation.py
investaholic_common/representation/proposal_representation.py
investaholic_common/representation/representation.py
investaholic_common/representation/ticker_representation.py
investaholic_common/representation/user_representation.py
investaholic_common-0.1.0.dist-info/METADATA
investaholic_common-0.1.0.dist-info/WHEEL
investaholic_common-0.1.0.dist-info/top_level.txt
investaholic_common-0.1.0.dist-info/RECORD
