Metadata-Version: 2.1
Name: investaholic-common
Version: 0.1.0
Summary: investaholic common classes
Author: Manuel Acquistapace
Author-email: manuel.acquistapace@student.supsi.ch
